palettum/__init__.py
palettum/cli.py
palettum/gif.dll
palettum/libpng16.dll
palettum/libsharpyuv.dll
palettum/libwebp.dll
palettum/mtpng.dll
palettum/palettum.cp38-win_amd64.pyd
palettum/turbojpeg.dll
palettum/zlib1.dll
palettum/palettes/Catppuccin Frappe.json
palettum/palettes/Catppuccin Latte.json
palettum/palettes/Catppuccin Macchiato.json
palettum/palettes/Catppuccin Mocha.json
palettum/palettes/Dracula.json
palettum/palettes/Nord.json
palettum/palettes/gruvbox.json
palettum/palettes/r_place 2022.json
palettum-0.4.8.dist-info/LICENSE
palettum-0.4.8.dist-info/METADATA
palettum-0.4.8.dist-info/WHEEL
palettum-0.4.8.dist-info/entry_points.txt
palettum-0.4.8.dist-info/top_level.txt
palettum-0.4.8.dist-info/RECORD
