Metadata-Version: 2.1
Name: palettum
Version: 0.4.8
Summary: Core functionality for the Palettum project.
Home-page: https://github.com/ArrowPC/palettum/
Author: ArrowPC
License: GNU Affero General Public License v3.0
Requires-Python: >=3.8
License-File: LICENSE
Requires-Dist: rich-click >=1.7.0
Provides-Extra: test
Requires-Dist: pytest >=6.0 ; extra == 'test'
